bot_formatter/__init__.py
bot_formatter/__main__.py
bot_formatter/run.py
bot_formatter/formatters/__init__.py
bot_formatter/formatters/dpy.py
bot_formatter/formatters/ezcord.py
bot_formatter/formatters/lang.py
bot_formatter/formatters/yml.py
bot_formatter-0.1.2.dist-info/licenses/LICENSE
bot_formatter-0.1.2.dist-info/METADATA
bot_formatter-0.1.2.dist-info/WHEEL
bot_formatter-0.1.2.dist-info/entry_points.txt
bot_formatter-0.1.2.dist-info/top_level.txt
bot_formatter-0.1.2.dist-info/RECORD
