Metadata-Version: 2.4
Name: bot-formatter
Version: 0.1.2
Summary: A formatter for Discord bots.
Author: tibue99
License: MIT
Project-URL: GitHub, https://github.com/CookieAppTeam/bot-formatter
Keywords: discord,discord.py,py-cord,ezcord,pre-commit
Classifier: Development Status :: 5 - Production/Stable
Classifier: License :: OSI Approved :: MIT License
Classifier: Intended Audience :: Developers
Classifier: Operating System :: OS Independent
Classifier: Topic :: Software Development :: Quality Assurance
Classifier: Programming Language :: Python :: 3.10
Classifier: Programming Language :: Python :: 3.11
Classifier: Programming Language :: Python :: 3.12
Classifier: Programming Language :: Python :: 3.13
Classifier: Programming Language :: Python :: 3.14
Requires-Python: >=3.10
License-File: LICENSE
Requires-Dist: libcst
Requires-Dist: PyYAML
Dynamic: license-file
